nos/__init__.py
nos/compat.py
nos/connection.py
nos/exceptions.py
nos/serializer.py
nos/transport.py
nos/client/__init__.py
nos/client/auth.py
nos/client/nos_client.py
nos/client/utils.py
nos_python3_sdk-1.0.2.dist-info/METADATA
nos_python3_sdk-1.0.2.dist-info/RECORD
nos_python3_sdk-1.0.2.dist-info/WHEEL
nos_python3_sdk-1.0.2.dist-info/top_level.txt
