Metadata-Version: 2.1
Name: nos-python3-sdk
Version: 1.0.2
Summary: NetEase Object Storage SDK For Python3
Home-page: https://c.163.com/
Author: nos-dev-new
Author-email: nos-dev@hz.netease.com
License: MIT License
Platform: UNKNOWN
Classifier: Development Status :: 5 - Production/Stable
Classifier: License :: OSI Approved :: MIT License
Classifier: Intended Audience :: Developers
Classifier: Operating System :: OS Independent
Classifier: Programming Language :: Python
Classifier: Programming Language :: Python :: 3
Classifier: Programming Language :: Python :: 3.5
Classifier: Programming Language :: Python :: 3.6
Classifier: Programming Language :: Python :: 3.7
Requires-Dist: urllib3 (<2.0,>=1.8)
Requires-Dist: certifi
